minecraft_recipe_parser_from_websites.py
minecraft_scrape_package-0.0.2.dist-info/licenses/LICENSE.txt
minecraft_scrape_package-0.0.2.dist-info/METADATA
minecraft_scrape_package-0.0.2.dist-info/WHEEL
minecraft_scrape_package-0.0.2.dist-info/top_level.txt
minecraft_scrape_package-0.0.2.dist-info/RECORD
